{
  "archivo_imagen": "clasificacion_20250908_121849_1.jpg",
  "timestamp_procesamiento": "2025-09-08T12:18:49.298550",
  "timestamp_captura": "20250908_121849",
  "tipo_analisis": "clasificacion",
  "version_metadatos": "1.0",
  "modelo": {
    "nombre": "CopleClasDef2C1V.onnx",
    "tipo": "clasificacion",
    "clases_disponibles": [
      "Aceptado",
      "Rechazado"
    ]
  },
  "imagen": {
    "resolucion": {
      "ancho": 640,
      "alto": 640,
      "canales": 3
    },
    "formato": "RGB",
    "tipo": "uint8"
  },
  "sistema": {
    "version": "1.0",
    "plataforma": "Linux",
    "framework": "ONNX Runtime"
  },
  "resultados": {
    "clasificacion": {
      "clase": "Aceptado",
      "confianza": 0.97061687707901,
      "tiempo_inferencia_ms": 41.33439064025879
    }
  },
  "tiempos": {
    "captura_ms": 50.780534744262695,
    "clasificacion_ms": 41.37730598449707,
    "total_ms": 41.37754440307617
  },
  "estadisticas": {
    "total_clasificaciones": 1,
    "confianza_promedio": 0.97061687707901,
    "confianza_maxima": 0.97061687707901,
    "confianza_minima": 0.97061687707901
  }
}